MANIFEST.in
README.md
setup.py
co2logserver/__init__.py
co2logserver/__main__.py
co2logserver/app.py
co2logserver/authentication.py
co2logserver/config.py
co2logserver/config_default.py
co2logserver/database.py
co2logserver/download.py
co2logserver/exceptions.py
co2logserver/index.py
co2logserver/upload.py
co2logserver/utils.py
co2logserver/version.py
co2logserver.egg-info/PKG-INFO
co2logserver.egg-info/SOURCES.txt
co2logserver.egg-info/dependency_links.txt
co2logserver.egg-info/requires.txt
co2logserver.egg-info/top_level.txt
co2logserver/templates/datapage.html
co2logserver/templates/errorMessage.html
co2logserver/templates/index.html
co2logserver/templates/upload.html