Metadata-Version: 2.1
Name: co2logserver
Version: 0.1.2
Summary: simple HTTP server for CO2 data logging
Home-page: https://gitlab.com/tue-umphy/co2mofetten/python3-co2logserver
Author: Yann Büchau
Author-email: nobodyinperson@gmx.de
License: GPLv3
Keywords: measurement,logging
Platform: UNKNOWN
Classifier: License :: OSI Approved :: GNU General Public License v3 (GPLv3)
Classifier: Programming Language :: Python :: 3.5
Classifier: Operating System :: OS Independent
Classifier: Topic :: Software Development :: Libraries :: Python Modules
Provides-Extra: msgpack
Provides-Extra: opensensemap
